{"level":0,"tags":[],"bienvenueRef":[],"title":"Dialogue - Aller au parc et anniversaire d’Akari","contents":{"0":{"tag":"ZGPAudio","args":["Aller au parc et anniversaire d’Akari-chan.m4a"]},"1":{"tag":"ZTJMarkdown","args":["### <u>Script : </u>"]},"2":{"tag":"ZTJRichJapText","args":[{"sentences":[{"japanese":"**<ruby>中村<rt>なかむら</rt></ruby>**：ルカさん、おはよう　ございます。","romaji":"**Nakamura**：ruka san, ohayō gozaimasu.","french":"Nakamura : Bonjour Lucas!","showFrench":false,"display":{"tag":"Japanese","args":[{"tag":"KanjiWithFurigana","args":[]}]}},{"japanese":"**ルカさん**：おはよう　ございます。ああ　あかりちゃん、おはよう。","romaji":"**Ruka san**：ohayō gozaimasu. a, akari chan, ohayō.","french":"Lucas : Bonjour, ah et bonjour Akari!","showFrench":false,"display":{"tag":"Japanese","args":[{"tag":"KanjiWithFurigana","args":[]}]}},{"japanese":"**あかり**：おはよう〜","romaji":"**Akari**： ohayō〜","french":"Akari : Bonjour!","showFrench":false,"display":{"tag":"Japanese","args":[{"tag":"KanjiWithFurigana","args":[]}]}},{"japanese":"**ルカさん（<ruby>中村<rt>なかむら</rt></ruby>に）**：<ruby>今日<rt>きょう</rt></ruby>の　**<ruby>予定<rt>よてい</rt></ruby>**は　<ruby>何<rt>なん</rt></ruby>ですか。","romaji":"**Ruka san（ nakamura ni ）**：kyō no **yotei** wa nan desu ka.","french":"Lucas (à Nakamura) : Qu'est ce que tu as de prévu aujourd'hui?","showFrench":false,"display":{"tag":"Japanese","args":[{"tag":"KanjiWithFurigana","args":[]}]}},{"japanese":"**<ruby>中村<rt>なかむら</rt></ruby>**：<ruby>今日<rt>きょう</rt></ruby>は　あかりちゃんと　**<ruby>公園<rt>こうえん</rt></ruby>**に　<ruby>行<rt>い</rt></ruby>くの。","romaji":"**Nakamura**：kyō wa akari chan to **kōen** ni iku no.","french":"Nakamura : Aujourd'hui avec Akari on va au parc.","showFrench":false,"display":{"tag":"Japanese","args":[{"tag":"KanjiWithFurigana","args":[]}]}},{"japanese":"**ルカさん**：<ruby>楽<rt>たの</rt></ruby>しそう！**いい　<ruby>天気<rt>てんき</rt></ruby>**　なので！","romaji":"**Ruka san**： tanoshi sō! **ii tenki** na no de !","french":"Lucas : ça a l'air sympa, comme il fait beau.","showFrench":false,"display":{"tag":"Japanese","args":[{"tag":"KanjiWithFurigana","args":[]}]}},{"japanese":"**<ruby>中村<rt>なかむら</rt></ruby>**：そう　なん　です。しかも、あかりちゃんの お<ruby>誕生<rt>たんじょう</rt></ruby><ruby>日<rt>び</rt></ruby>　なので。","romaji":"**Nakamura**： sō nan desu. shikamo, akari chan no o-tanjōbi na no de.","french":"Nakamura : Oui, et en plus, c'est l'anniversaire d'Akari.","showFrench":false,"display":{"tag":"Japanese","args":[{"tag":"KanjiWithFurigana","args":[]}]}},{"japanese":"**ルカさん**：ええ〜 あかりちゃん、**お<ruby>誕生<rt>たんじょう</rt></ruby><ruby>日<rt>び</rt></ruby>**　おめでとう。","romaji":"**Ruka san**：ē, akari chan, **o tanjōbi** omedetō.","french":"Lucas : Bonne anniversaire Akari!","showFrench":false,"display":{"tag":"Japanese","args":[{"tag":"KanjiWithFurigana","args":[]}]}},{"japanese":"**あかり**：ありがとう　ございます。","romaji":"**Akari**：arigatō gozaimasu.","french":"Akari : Merci!","showFrench":false,"display":{"tag":"Japanese","args":[{"tag":"KanjiWithFurigana","args":[]}]}},{"japanese":"**ルカさん**：**<ruby>何<rt>なん</rt></ruby><ruby>歳<rt>さい</rt></ruby>**に　なったの？","romaji":"**Ruka san**：**nan sai** ni natta no ?","french":"Lucas : Quel âge ça te fait?","showFrench":false,"display":{"tag":"Japanese","args":[{"tag":"KanjiWithFurigana","args":[]}]}},{"japanese":"**あかり**：**<ruby>六<rt>ろく</rt></ruby><ruby>歳<rt>さい</rt></ruby>**に　なったの。","romaji":"**Akari**：**roku sai** ni natta no.","french":"Akari : 6 ans.","showFrench":false,"display":{"tag":"Japanese","args":[{"tag":"KanjiWithFurigana","args":[]}]}},{"japanese":"**ルカさん**：わあ〜　すごい！　じゃあ　<ruby>楽<rt>たの</rt></ruby>しんでね。","romaji":"**Ruka san**： wā sugoi ! jā tanoshinde ne.","french":"Lucas : Incroyable! Bon, profites bien!","showFrench":false,"display":{"tag":"Japanese","args":[{"tag":"KanjiWithFurigana","args":[]}]}},{"japanese":"**<ruby>中村<rt>なかむら</rt></ruby>**：ありがとう　ございます！　ルカさんも！","romaji":"**Nakamura**：arigatō gozaimasu ! ruka san mo !","french":"Nakamura : Merci beaucoup! Toi aussi Lucas!","showFrench":false,"display":{"tag":"Japanese","args":[{"tag":"KanjiWithFurigana","args":[]}]}},{"japanese":"**ルカさん**：ありがとう　ございます！","romaji":"**Ruka san**：arigatō gozaimasu !","french":"Lucas : Merci beaucoup!","showFrench":false,"display":{"tag":"Japanese","args":[{"tag":"KanjiWithFurigana","args":[]}]}}],"mode":{"tag":"RJTStudent","args":[]}}]},"3":{"tag":"ZTJMarkdown","args":["### <u>Vocabulaire :</u>"]},"4":{"tag":"ZTJRichJapText","args":[{"sentences":[{"japanese":"• <ruby>予定<rt>よてい</rt></ruby>　= Ce que vous avez de prévu / planning","romaji":"• yotei = Ce que vous avez de prévu / planning","french":"","showFrench":false,"display":{"tag":"Japanese","args":[{"tag":"KanjiWithFurigana","args":[]}]}},{"japanese":"• <ruby>公園<rt>こうえん</rt></ruby> = Parc","romaji":"• kōen = Parc","french":"","showFrench":false,"display":{"tag":"Japanese","args":[{"tag":"KanjiWithFurigana","args":[]}]}},{"japanese":"• いい<ruby>天気<rt>てんき</rt></ruby> = Beau temps","romaji":"• ii tenki = Beau temps","french":"","showFrench":false,"display":{"tag":"Japanese","args":[{"tag":"KanjiWithFurigana","args":[]}]}},{"japanese":"• <ruby>楽<rt>たの</rt></ruby>しんでね = Amusez-vous","romaji":"• tanoshinde ne = Amusez-vous","french":"","showFrench":false,"display":{"tag":"Japanese","args":[{"tag":"KanjiWithFurigana","args":[]}]}},{"japanese":"• <ruby>誕生<rt>たんじょう</rt></ruby><ruby>日<rt>び</rt></ruby> = Anniversaire","romaji":"• tanjō bi = Anniversaire","french":"","showFrench":false,"display":{"tag":"Japanese","args":[{"tag":"KanjiWithFurigana","args":[]}]}},{"japanese":"• <ruby>何<rt>なん</rt></ruby><ruby>歳<rt>さい</rt></ruby> = Quel âge","romaji":"• nan sai = Quel âge","french":"","showFrench":false,"display":{"tag":"Japanese","args":[{"tag":"KanjiWithFurigana","args":[]}]}},{"japanese":"• <ruby>六<rt>ろく</rt></ruby><ruby>歳<rt>さい</rt></ruby> = Six ans","romaji":"• roku sai = Six ans","french":"","showFrench":false,"display":{"tag":"Japanese","args":[{"tag":"KanjiWithFurigana","args":[]}]}}],"mode":{"tag":"RJTStudent","args":[]}}]}}}